cyclophaser/__init__.py
cyclophaser/determine_periods.py
cyclophaser/find_stages.py
cyclophaser/lanczos_filter.py
cyclophaser/plots.py
cyclophaser/example_data/example_file.csv
tests/__init__.py
tests/test_determine_periods.py
cyclophaser-1.9.4.dist-info/LICENSE
cyclophaser-1.9.4.dist-info/METADATA
cyclophaser-1.9.4.dist-info/WHEEL
cyclophaser-1.9.4.dist-info/top_level.txt
cyclophaser-1.9.4.dist-info/RECORD
